newsbot/__init__.py
newsbot/bot.py
newsbot/feed.py
newsbot/feeds.yml
lxmfy_news_bot-0.7.0.dist-info/METADATA
lxmfy_news_bot-0.7.0.dist-info/WHEEL
lxmfy_news_bot-0.7.0.dist-info/entry_points.txt
lxmfy_news_bot-0.7.0.dist-info/licenses/LICENSE
lxmfy_news_bot-0.7.0.dist-info/RECORD
