Metadata-Version: 2.4
Name: lxmfy-news-bot
Version: 0.7.0
Summary: LXMFy News Bot using RSS and trafilatura to fetch full-text
License-File: LICENSE
Author: Ivan
Requires-Python: >=3.11
Classifier: Programming Language :: Python :: 3
Classifier: Programming Language :: Python :: 3.11
Classifier: Programming Language :: Python :: 3.12
Classifier: Programming Language :: Python :: 3.13
Classifier: Programming Language :: Python :: 3.14
Requires-Dist: feedparser (>=6.0.12,<7.0.0)
Requires-Dist: lxmfy (>=1.0.3,<2.0.0)
Requires-Dist: pytz (>=2025.2,<2026.0.0)
Requires-Dist: pyyaml (>=6.0.3,<7.0.0)
Requires-Dist: trafilatura (>=2.0.0,<3.0.0)
